brishgarden/__init__.py
brishgarden/garden.py
brishgarden-0.2.3.1.dist-info/entry_points.txt
brishgarden-0.2.3.1.dist-info/WHEEL
brishgarden-0.2.3.1.dist-info/METADATA
brishgarden-0.2.3.1.dist-info/RECORD
